CHANGELOG.txt
LICENCE.txt
MANIFEST.in
README.txt
setup.py
BinMySQL/__init__.py
BinMySQL.egg-info/PKG-INFO
BinMySQL.egg-info/SOURCES.txt
BinMySQL.egg-info/dependency_links.txt
BinMySQL.egg-info/requires.txt
BinMySQL.egg-info/top_level.txt