Metadata-Version: 1.1
Name: BinMySQL
Version: 0.0.5
Summary: Quick and intuitive MySQL Connector
Home-page: UNKNOWN
Author: Robin Chong
Author-email: wafturerobin.dev@gmail.com
License: MIT
Keywords: MySQL
Platform: UNKNOWN
Classifier: Development Status :: 5 - Production/Stable
Classifier: Intended Audience :: Education
Classifier: Operating System :: Microsoft :: Windows :: Windows 10
Classifier: License :: OSI Approved :: MIT License
Classifier: Programming Language :: Python :: 3
